uProcess/__init__.py
uProcess/uProcess.pyd
LabSmith_uProcess-1.9.0.3.12.dist-info/METADATA
LabSmith_uProcess-1.9.0.3.12.dist-info/WHEEL
LabSmith_uProcess-1.9.0.3.12.dist-info/top_level.txt
LabSmith_uProcess-1.9.0.3.12.dist-info/RECORD
