Metadata-Version: 2.1
Name: LabSmith_uProcess
Version: 1.9.0.3.12
Summary: Python x32 support for controlling LabSmith uDevices
Home-page: http://www.labsmith.com
Author: LabSmith
Author-email: ecummings@labsmith.com
Classifier: Programming Language :: Python :: 3
Classifier: License :: OSI Approved :: MIT License
Classifier: Operating System :: Microsoft :: Windows
Classifier: Natural Language :: English
Requires-Python: >=3.12,<3.13
